umidi/__init__.py
umidi-0.1.0.dist-info/METADATA
umidi-0.1.0.dist-info/WHEEL
umidi-0.1.0.dist-info/RECORD
