Metadata-Version: 2.4
Name: umidi
Version: 0.1.0
Summary: 🎹 Fastest Python MIDI file reading
Project-URL: GitHub, https://github.com/BrokenSource/umidi/
Author-email: Tremeschin <29046864+Tremeschin@users.noreply.github.com>
Requires-Python: >=3.10
Requires-Dist: attrs~=25.3.0
